eznbtemplater/__init__.py
eznbtemplater/eznbtemplater.py
eznbtemplater/templates/calculation_note.ipynb
eznbtemplater-0.1.5.dist-info/METADATA
eznbtemplater-0.1.5.dist-info/WHEEL
eznbtemplater-0.1.5.dist-info/licenses/LICENSE
eznbtemplater-0.1.5.dist-info/RECORD
