Metadata-Version: 2.3
Name: eznbtemplater
Version: 0.1.5
Summary: Generate PDF and Jupyter Notebook files from a Notebook template
Project-URL: homepage, https://github.com/miek770/eznbtemplater
Project-URL: issues, https://github.com/miek770/eznbtemplater/issues
Author-email: Michel Lavoie <lavoie.michel@gmail.com>
Classifier: License :: OSI Approved :: MIT License
Classifier: Operating System :: OS Independent
Classifier: Programming Language :: Python :: 3
Requires-Python: >=3.10
Requires-Dist: nbconvert>=7.16.4
Requires-Dist: nbformat>=5.10.4
